{
    "parent": "minecraft:item/handheld_rod",
    "textures": {
      "layer0": "minecraft:item/warped_fungus_on_a_stick"
    },
    "overrides": [
      {
        "predicate": {
          "custom_model_data": 880000
        },
        "model": "cgn:item/automatic_bow"
      },
      {
        "predicate": {
          "custom_model_data": 880001
        },
        "model": "cgn:item/electromodulator"
      },
      {
        "predicate": {
          "custom_model_data": 880002
        },
        "model": "cgn:entity/electroplasm_wave"
      },
      {
        "predicate": {
          "custom_model_data": 880003
        },
        "model": "cgn:item/midnight_rose_seed"
      },
      {
        "predicate": {
          "custom_model_data": 880004
        },
        "model": "cgn:block/midnight_rose_age0"
        },
        {
        "predicate": {
          "custom_model_data": 880005
        },
        "model": "cgn:block/midnight_rose_age1"
        },
        {
        "predicate": {
          "custom_model_data": 880006
        },
        "model": "cgn:block/midnight_rose_age2"
        },
        {
        "predicate": {
          "custom_model_data": 880007
        },
        "model": "cgn:block/midnight_rose_age3"
        },
        {
        "predicate": {
          "custom_model_data": 880008
        },
        "model": "cgn:block/wispthorn"
        }
    ]
}